README.rst
setup.py
django_pounce.egg-info/PKG-INFO
django_pounce.egg-info/SOURCES.txt
django_pounce.egg-info/dependency_links.txt
django_pounce.egg-info/top_level.txt
pounce/__init__.py
pounce/middleware.py