Metadata-Version: 1.1
Name: django-pounce
Version: 0.2.0
Summary: Django middleware for preloading resources using the HTTP Link header
Home-page: https://github.com/jacobbudin/django-pounce
Author: Jacob Budin
Author-email: self@jacobbudin.com
License: BSD
Keywords: django preload performance
Platform: UNKNOWN
Classifier: Development Status :: 3 - Alpha
Classifier: Environment :: Web Environment
Classifier: Intended Audience :: Developers
Classifier: License :: OSI Approved :: BSD License
Classifier: Operating System :: OS Independent
Classifier: Programming Language :: Python
Classifier: Framework :: Django
Classifier: Topic :: Utilities
